{
  "runtimeVersion": "1.0.0",
  "runtimeStage": "early-runtime",
  "run": {
    "id": "roak-run-1781707481519",
    "app": "RuleOak Technical Consultant Demo",
    "status": "completed",
    "startedAt": "2026-06-17T14:44:41.519Z",
    "completedAt": "2026-06-17T14:44:41.520Z",
    "metadata": {
      "demo": "technical-consultant-demo",
      "caseId": "CASE-2026-001"
    }
  },
  "boundary": "local_only",
  "summary": {
    "title": "Checkout service latency and error increase",
    "probableCause": "Database connection pool saturation affecting checkout-service request handling.",
    "confidence": "medium-high",
    "proposedAction": "restart.service",
    "policyDecision": "approval_required",
    "approvalStatus": "pending"
  },
  "output": {
    "demo": "technical-consultant-demo",
    "case": {
      "id": "CASE-2026-001",
      "service": "checkout-service",
      "severity": "high",
      "title": "Checkout service latency and error increase"
    },
    "probableCause": "Database connection pool saturation affecting checkout-service request handling.",
    "confidence": "medium-high",
    "recommendation": [
      "Do not make an automatic production change.",
      "Capture current database connection, recent deployment, and traffic context.",
      "Escalate to the service owner if saturation persists.",
      "Consider restart or capacity change only after approval."
    ],
    "proposedAction": "restart.service",
    "policyDecision": {
      "action": "restart.service",
      "decision": "approval_required",
      "allowedNow": false,
      "approvalRequired": true,
  ...
}